{
  "id": "cmnoaa8g600gpcgtdcaw540dh",
  "tanggal": "2026-08-03T00:00:00.000Z",
  "namaHariBesar": null,
  "namaMinggu": null,
  "topik": null,
  "topikBatak": null,
  "evangelium": null,
  "epistel": null,
  "phdNaposobulung": null,
  "phdIna": null,
  "phdAma": null,
  "phdRemaja": null,
  "phdLansia": null,
  "jamitaSkolaMinggu": null,
  "renunganJudul": "Rom 12 : 1 - 2",
  "renunganIsi": "Karena itu, saudara-saudara, demi kemurahan Allah aku menasihatkan kamu, supaya kamu mempersembahkan tubuhmu sebagai persembahan yang hidup, yang kudus dan yang berkenan kepada Allah: itu adalah ibadahmu yang sejati. Janganlah kamu menjadi serupa dengan dunia ini, tetapi berubahlah oleh pembaharuan budimu, sehingga kamu dapat membedakan manakah kehendak Allah, apa yang baik, yang berkenan kepada Allah dan yang sempurna.",
  "renunganIsiBatak": "Na huapoi ma hamu, ale angka dongan, marhitehite asi ni roha ni Debata: Pasahat hamu ma dagingmuna bahen pelean na mangolu, na badia, na hinalomohon ni Debata; i ma hadaulaton ni na marroha. Jala unang gabe sarombang hamu dohot portibi on; alai gabe imbaru ma hamu, dung muba pingkiranmuna, asa tau hamu manimbangi lomo ni roha ni Debata, i ma nauli, na hinalashonna dohot na sun denggan.",
  "renunganEpistelIsi": null,
  "renunganEpistelIsiBatak": null,
  "renunganEvangeliumIsi": null,
  "renunganEvangeliumIsiBatak": null,
  "warnaLiturgi": null,
  "nyanyian": "BE. 467 : 4",
  "bacaanPagi": "Poda 15 : 1 - 16",
  "bacaanMalam": "Markus 7 : 24 - 30",
  "instagramEmbedUrl": null,
  "tiktokEmbedUrl": null,
  "renunganPenulisId": null,
  "renunganPenulisType": null,
  "renunganPenulisNama": null,
  "renunganPenulisFoto": null,
  "createdBy": "sync-almanak",
  "createdAt": "2026-04-07T07:14:25.734Z",
  "updatedAt": "2026-04-07T07:14:25.734Z",
  "bulanan": {
    "id": "cmmpw5666000jwotdn9bbl3kr",
    "tahun": 2026,
    "bulan": 8,
    "temaBhs": "PERCAYALAH KEPADA TUHAN DAN LAKUKANLAH YANG BAIK",
    "temaBtk": "MARHAPOSAN TU JAHOWA MA HO JALA ULAHON NA DENGGAN",
    "ayatNats": "Psalmen 37 : 3",
    "ayatBhs": "Percayalah kepada TUHAN dan lakukanlah yang baik, diamlah di negeri dan berlakulah setia,",
    "ayatBtk": "Sai marhaposan tu Jahowa ma ho jala ulahon na denggan; inganhon ma tano i jala radoti haburjuon.",
    "endeNo": "BE. No. 403 : 2",
    "createdAt": "2026-03-14T05:34:24.894Z",
    "updatedAt": "2026-04-07T07:14:05.444Z"
  }
}
